moor/__init__.py
moor/cli.py
moor/config.py
moor-0.0.2.dist-info/LICENSE
moor-0.0.2.dist-info/METADATA
moor-0.0.2.dist-info/WHEEL
moor-0.0.2.dist-info/entry_points.txt
moor-0.0.2.dist-info/top_level.txt
moor-0.0.2.dist-info/RECORD
