Metadata-Version: 2.1
Name: moor
Version: 0.0.2
Summary: A commandline tool for managing docker builds
Home-page: https://github.com/ejfitzgerald/moor
Author: Ed FitzGerald
Author-email: edward.fitzgerald@fetch.ai
License: UNKNOWN
Platform: UNKNOWN
Classifier: Programming Language :: Python :: 3
Classifier: License :: OSI Approved :: MIT License
Classifier: Operating System :: OS Independent
Requires-Dist: toml
Provides-Extra: dev
Requires-Dist: check-manifest ; extra == 'dev'
Provides-Extra: test
Requires-Dist: coverage ; extra == 'test'
Requires-Dist: pytest ; extra == 'test'
